watson_overtime/__init__.py
watson_overtime/__main__.py
watson_overtime/click_timedelta.py
watson_overtime/config.py
watson_overtime/main.py
watson_overtime/watson_overtime.py
watson_overtime-0.3.0.dist-info/entry_points.txt
watson_overtime-0.3.0.dist-info/LICENSE
watson_overtime-0.3.0.dist-info/WHEEL
watson_overtime-0.3.0.dist-info/METADATA
watson_overtime-0.3.0.dist-info/RECORD
